tinycat/__init__.py
tinycat/cli.py
tinycat/translate.py
tinycat-0.1.1.dist-info/LICENSE
tinycat-0.1.1.dist-info/METADATA
tinycat-0.1.1.dist-info/WHEEL
tinycat-0.1.1.dist-info/top_level.txt
tinycat-0.1.1.dist-info/RECORD
