Metadata-Version: 2.1
Name: tinycat
Version: 0.1.1
Summary: A tiny Computer-Assisted Translation tool
Home-page: https://github.com/kbobrowski/tinycat
Author: Kamil Bobrowski
Author-email: kamil.bobrowski@gmail.com
License: UNKNOWN
Platform: UNKNOWN
Classifier: Programming Language :: Python :: 3
Classifier: License :: OSI Approved :: MIT License
Classifier: Operating System :: OS Independent
Requires-Python: >=3.6
Requires-Dist: click
Requires-Dist: deep-translator
